patchwise/__init__.py
patchwise/logger_setup.py
patchwise/main.py
patchwise/patch_review/__init__.py
patchwise/patch_review/decorators.py
patchwise/patch_review/kernel_tree.py
patchwise/patch_review/patch_review.py
patchwise/patch_review/ai_review/__init__.py
patchwise/patch_review/ai_review/ai_code_review.py
patchwise/patch_review/ai_review/ai_review.py
patchwise/patch_review/ai_review/llm_commit_audit.py
patchwise/patch_review/static_analysis/__init__.py
patchwise/patch_review/static_analysis/checkpatch.py
patchwise/patch_review/static_analysis/coccicheck.py
patchwise/patch_review/static_analysis/dt_check.py
patchwise/patch_review/static_analysis/dtbs_check.py
patchwise/patch_review/static_analysis/sparse.py
patchwise/patch_review/static_analysis/static_analysis.py
patchwise-0.2.1.dist-info/licenses/LICENSE.txt
patchwise-0.2.1.dist-info/METADATA
patchwise-0.2.1.dist-info/WHEEL
patchwise-0.2.1.dist-info/entry_points.txt
patchwise-0.2.1.dist-info/top_level.txt
patchwise-0.2.1.dist-info/RECORD
