Metadata-Version: 2.4
Name: patchwise
Version: 0.2.1
Summary: A tool for reviewing kernel patches
Author-email: David Gantman <dgantman@qti.qualcomm.com>
Requires-Python: >=3.10
License-File: LICENSE.txt
Requires-Dist: Sphinx>=8.1.3
Requires-Dist: litellm>=1.74
Requires-Dist: cachetools>=5.5.2
Requires-Dist: yamllint>=1.26.3
Requires-Dist: ply>=3.11
Requires-Dist: GitPython>=3.1.44
Requires-Dist: codespell>=2.4.1
Requires-Dist: pytest>=8.3.5
Requires-Dist: rich-argparse>=1.7.0
Requires-Dist: tqdm>=4.67.1
Dynamic: license-file
